[
  {
    "id": 1,
    "img": "/imgregistro.jpg",
    "title": "Casa en la Playa",
    "description": "Hermosa casa con vista al mar, 3 habitaciones, 2 baños.",
    "bedroom":3,
    "bathroom":2,
    "price": 3000,
    "additionalImages": [
      "/imgportada.jpg",
      "/imgregistro.jpg",
      "/imguser.jpg"
    ]
  },
  {
    "id": 2,
    "img": "/imgsesion.jpg",
    "title": "Apartamento en la Ciudad",
    "description": "Moderno apartamento en el centro, 2 habitaciones, 1 baño.",
    "bedroom":2,
    "bathroom":1,
    "price": 4500,
    "additionalImages": [
      "/imgregistro.jpg",
      "/imgadmin.jpg",
      "/imgportada.jpg"
    ]
  },
  {
    "id": 3,
    "img": "/imgadmin.jpg",
    "title": "Casa en el Campo",
    "description": "Amplia casa con jardín, 4 habitaciones, 3 baños.",
    "bedroom":4,
    "bathroom":3,
    "price": 2000,
    "additionalImages": [
      "/imgsesion.jpg",
      "/imguser.jpg",
      "/imgadmin.jpg"
    ]
  }
]
